{"BaseModel.6fdcfec2-7ba0-49be-af9f-9409582f364a": {"id": "6fdcfec2-7ba0-49be-af9f-9409582f364a", "created_at": "2023-02-18T19:35:17.900806", "updated_at": "2023-02-18T19:35:17.900819", "name": "My_First_Model", "my_number": 89, "__class__": "BaseModel"}, "BaseModel.c0d9c602-d6bc-42bf-ad2b-d3de49779bcb": {"id": "c0d9c602-d6bc-42bf-ad2b-d3de49779bcb", "created_at": "2023-02-18T19:35:23.591454", "updated_at": "2023-02-18T19:35:23.591468", "name": "My_First_Model", "my_number": 89, "__class__": "BaseModel"}, "BaseModel.f358e45b-f32b-4061-a6b3-6280e8cd34d2": {"id": "f358e45b-f32b-4061-a6b3-6280e8cd34d2", "created_at": "2023-02-18T19:35:25.554548", "updated_at": "2023-02-18T19:35:25.554562", "name": "My_First_Model", "my_number": 89, "__class__": "BaseModel"}, "BaseModel.c7e9a444-2df1-4c28-b8c9-ab5dc14f0929": {"id": "c7e9a444-2df1-4c28-b8c9-ab5dc14f0929", "created_at": "2023-02-18T19:35:27.985176", "updated_at": "2023-02-18T19:35:27.985184", "name": "My_First_Model", "my_number": 89, "__class__": "BaseModel"}, "BaseModel.6f0a7502-15dd-47bc-b51d-2761fba573a1": {"id": "6f0a7502-15dd-47bc-b51d-2761fba573a1", "created_at": "2023-02-18T19:35:29.153149", "updated_at": "2023-02-18T19:35:29.153163", "name": "My_First_Model", "my_number": 89, "__class__": "BaseModel"}}